{
  "schemaVersion": 1,
  "fetchedAt": 1781687955995,
  "contentHash": "344ce178539e",
  "breaking": [
    {
      "title": "UK investigating reports Russian warship fired warning shots near yacht in English Channel",
      "summary": "The retired couple tell BBC Newsnight they tried to show the warship they had changed course in the English Channel before the shots were fired.",
      "source": "BBC World",
      "sourceGroup": "bbc",
      "url": "https://www.bbc.com/news/articles/c20yzm84r7lo?at_medium=RSS&at_campaign=rss",
      "publishedAt": 1781685504000,
      "category": "world",
      "region": "in",
      "language": "en",
      "id": "fb048b35c4de6aab",
      "suppressionReason": null,
      "isBreaking": true,
      "breakingScore": 4.443,
      "breakingReasons": [
        "multi_source_velocity",
        "severity_lexicon"
      ],
      "sourceCount": 2,
      "allSources": [
        "bbc",
        "the_hindu"
      ],
      "firstSeen": 1781685076000
    },
    {
      "title": "24-Year-Old Indian Techie Among 11 Skydivers Killed In Missouri Plane Crash",
      "summary": "Datla was a technology professional based in the Kansas City",
      "source": "NDTV",
      "sourceGroup": "ndtv",
      "url": "https://www.ndtv.com/world-news/24-year-old-indian-techie-sai-karthik-varma-datla-among-11-skydivers-killed-in-missouri-plane-crash-11648233#publisher=newsstand",
      "publishedAt": 1781686019000,
      "category": "topStories",
      "region": "in",
      "language": "en",
      "id": "718327ca1a84371a",
      "suppressionReason": null,
      "isBreaking": true,
      "breakingScore": 3.955,
      "breakingReasons": [
        "severity_lexicon"
      ],
      "sourceCount": 2,
      "allSources": [
        "ndtv",
        "the_hindu"
      ],
      "firstSeen": 1781678123000
    },
    {
      "title": "\"Ask Amit Shah\": Samajwadi Party MP After UP Minister's 'Split Soon' Claim",
      "summary": "Samajwadi Party MP Ram Gopal has dismissed OP Rajbhar's charge",
      "source": "NDTV",
      "sourceGroup": "ndtv",
      "url": "https://www.ndtv.com/india-news/up-minister-om-prakash-rajbhar-claims-akhilesh-yadavs-samajwadi-party-going-to-split-soon-11648148#publisher=newsstand",
      "publishedAt": 1781686465000,
      "category": "topStories",
      "region": "in",
      "language": "en",
      "id": "a6d8c3b6d71c8014",
      "suppressionReason": null,
      "isBreaking": true,
      "breakingScore": 2.965,
      "breakingReasons": [
        "multi_source_velocity"
      ],
      "sourceCount": 2,
      "allSources": [
        "ndtv",
        "the_hindu"
      ],
      "firstSeen": 1781686016000
    },
    {
      "title": "Video: 2 Men Throw Petrol Bombs At RSS Office In Ranchi, BJP Demands Probe",
      "summary": "The criminals immediately fled the scene.",
      "source": "NDTV",
      "sourceGroup": "ndtv",
      "url": "https://www.ndtv.com/india-news/video-2-men-throw-petrol-bombs-at-rss-office-in-ranchi-bjp-demands-probe-11648213#publisher=newsstand",
      "publishedAt": 1781684025000,
      "category": "topStories",
      "region": "in",
      "language": "en",
      "id": "e58a4b1f5e999085",
      "suppressionReason": null,
      "isBreaking": true,
      "breakingScore": 2.909,
      "breakingReasons": [
        "multi_source_velocity"
      ],
      "sourceCount": 2,
      "allSources": [
        "ndtv",
        "the_hindu"
      ],
      "firstSeen": 1781682982000
    },
    {
      "title": "Every Step Will Be Taken In Interest Of 22 Lakh Young Minds: Exam Body Chief On Telegram Ban",
      "summary": "Telegram Ban: The NTA chief said that the government's priority was to conduct a safe and secure re-NEET.",
      "source": "NDTV India",
      "sourceGroup": "ndtv",
      "url": "https://www.ndtv.com/education/neet-ug-2026-re-exam-every-step-will-be-taken-in-interest-of-22-lakh-young-minds-says-exam-body-nta-chief-11648137#publisher=newsstand",
      "publishedAt": 1781682802000,
      "category": "india",
      "region": "in",
      "language": "en",
      "id": "25fc7d0bbeba63b5",
      "suppressionReason": null,
      "isBreaking": true,
      "breakingScore": 2.881,
      "breakingReasons": [
        "multi_source_velocity"
      ],
      "sourceCount": 2,
      "allSources": [
        "bbc",
        "ndtv"
      ],
      "firstSeen": 1781679387000
    },
    {
      "title": "SpaceX Mania: How Elon Musk's rocket giant became Wall Street's biggest story",
      "summary": "SpaceX’s record-breaking IPO and soaring valuation have captivated Wall Street. Backed by Elon Musk’s vision, investors are betting on growth across space technology, Starlink, artificial intelligence, and enterprise software.",
      "source": "Economic Times",
      "sourceGroup": "economic_times",
      "url": "https://economictimes.indiatimes.com/markets/us-stocks/news/spacex-mania-how-elon-musks-rocket-giant-became-wall-streets-biggest-story/slideshow/131791096.cms",
      "publishedAt": 1781680636000,
      "category": "topStories",
      "region": "in",
      "language": "en",
      "id": "f1b073f2fc82565b",
      "suppressionReason": null,
      "isBreaking": true,
      "breakingScore": 2.831,
      "breakingReasons": [
        "multi_source_velocity"
      ],
      "sourceCount": 2,
      "allSources": [
        "economic_times",
        "times_of_india"
      ],
      "firstSeen": 1781678744000
    },
    {
      "title": "At 80, Trump is among the world's oldest leaders — but not the oldest",
      "summary": "<img align=\"left\" border=\"0\" hspace=\"10\" src=\"https://timesofindia.indiatimes.com/photo/131789212.cms\" style=\"margin-top: 3px; margin-right: 5px;\" />",
      "source": "Times of India",
      "sourceGroup": "times_of_india",
      "url": "https://timesofindia.indiatimes.com/world/rest-of-world/at-80-trump-is-among-the-worlds-oldest-leaders-but-not-the-oldest/articleshow/131789212.cms",
      "publishedAt": 1781679678000,
      "category": "india",
      "region": "in",
      "language": "en",
      "id": "10f1d38a043a59f6",
      "suppressionReason": null,
      "isBreaking": true,
      "breakingScore": 2.808,
      "breakingReasons": [
        "multi_source_velocity"
      ],
      "sourceCount": 2,
      "allSources": [
        "the_hindu",
        "times_of_india"
      ],
      "firstSeen": 1781678311000
    },
    {
      "title": "Bengaluru murder: Woman strangled to death by live-in partner in Malleswaram",
      "summary": "The police have arrested 25-year-old Sharath, who works as a water tanker driver",
      "source": "The Hindu",
      "sourceGroup": "the_hindu",
      "url": "https://www.thehindu.com/news/cities/bangalore/bengaluru-murder-woman-strangled-to-death-by-live-in-partner-in-malleswaram/article71112784.ece",
      "publishedAt": 1781687047000,
      "category": "topStories",
      "region": "in",
      "language": "en",
      "id": "19cc9ecf92083750",
      "suppressionReason": null,
      "isBreaking": true,
      "breakingScore": 2.479,
      "breakingReasons": [
        "severity_lexicon"
      ],
      "sourceCount": 1,
      "allSources": [
        "the_hindu"
      ],
      "firstSeen": 1781687047000
    }
  ]
}