{
  "schemaVersion": 1,
  "fetchedAt": 1782914214866,
  "contentHash": "bee2b143ad17",
  "breaking": [
    {
      "title": "\"Cremated Him With His Cricket Ball\": Family Of Boy Killed In Mumbai Tree Collapse",
      "summary": "Vihaan Srivastava, 11-year-old, killed in Mumbai tree collapse",
      "source": "NDTV",
      "sourceGroup": "ndtv",
      "url": "https://www.ndtv.com/india-news/cremated-him-with-his-cricket-ball-family-of-boy-killed-in-mumbai-tree-collapse-11712985#publisher=newsstand",
      "publishedAt": 1782909226000,
      "category": "topStories",
      "region": "in",
      "language": "en",
      "id": "f8e5442e1780c5f2",
      "suppressionReason": null,
      "isBreaking": true,
      "breakingScore": 5.885,
      "breakingReasons": [
        "multi_source_velocity",
        "severity_lexicon"
      ],
      "sourceCount": 2,
      "allSources": [
        "bbc",
        "ndtv"
      ],
      "firstSeen": 1782905085000
    },
    {
      "title": "Indian-origin truck driver killed in fuel tanker crash in Australia; wife says he was 25 years old",
      "summary": "<img align=\"left\" border=\"0\" hspace=\"10\" src=\"https://timesofindia.indiatimes.com/photo/132079044.cms\" style=\"margin-top: 3px; margin-right: 5px;\" />A heartbreaking incident unfolded on Victoria's Princes Freeway, taking the life of 25-year-old Ashwani Sharma, an Indian-origin truck driver. His fuel tanker overturned close to Warragul, leading to major road closures and a hazardous spill. In the wake of this tragedy, Sharma's wife has voiced her sorrow and is seeking community support to cope with the significant emotional and financial burdens following his unexpected demise.",
      "source": "Times of India",
      "sourceGroup": "times_of_india",
      "url": "https://timesofindia.indiatimes.com/world/rest-of-world/indian-origin-truck-driver-ashwani-sharma-killed-in-fuel-tanker-crash-in-australia-wife-says-he-was-just-25-years-old/articleshow/132079044.cms",
      "publishedAt": 1782907532000,
      "category": "india",
      "region": "in",
      "language": "en",
      "id": "170fb3a27f00761c",
      "suppressionReason": null,
      "isBreaking": true,
      "breakingScore": 3.845,
      "breakingReasons": [
        "severity_lexicon"
      ],
      "sourceCount": 1,
      "allSources": [
        "times_of_india"
      ],
      "firstSeen": 1782907532000
    },
    {
      "title": "'Neither side thinks they've lost': Iran determined to keep Hormuz control, even by force",
      "summary": "<img align=\"left\" border=\"0\" hspace=\"10\" src=\"https://timesofindia.indiatimes.com/photo/132111712.cms\" style=\"margin-top: 3px; margin-right: 5px;\" />",
      "source": "Times of India",
      "sourceGroup": "times_of_india",
      "url": "https://timesofindia.indiatimes.com/world/middle-east/neither-side-thinks-theyve-lost-iran-determined-to-keep-hormuz-control-even-by-force/articleshow/132111712.cms",
      "publishedAt": 1782906297000,
      "category": "india",
      "region": "in",
      "language": "en",
      "id": "3104cb6d1499eb5c",
      "suppressionReason": null,
      "isBreaking": true,
      "breakingScore": 2.817,
      "breakingReasons": [
        "multi_source_velocity"
      ],
      "sourceCount": 2,
      "allSources": [
        "the_hindu",
        "times_of_india"
      ],
      "firstSeen": 1782903244000
    },
    {
      "title": "Two Hampshire officers face misconduct probe over treatment of teen stabbed by Sikh man Vickrum Digwa",
      "summary": "<img align=\"left\" border=\"0\" hspace=\"10\" src=\"https://timesofindia.indiatimes.com/photo/132112986.cms\" style=\"margin-top: 3px; margin-right: 5px;\" />",
      "source": "Times of India",
      "sourceGroup": "times_of_india",
      "url": "https://timesofindia.indiatimes.com/world/uk/two-hampshire-officers-face-gross-misconduct-probe-after-handcuffing-teen-stabbed-by-sikh-man-vickrum-singh-digwa/articleshow/132112986.cms",
      "publishedAt": 1782903813000,
      "category": "india",
      "region": "in",
      "language": "en",
      "id": "d49823b7b2eb5961",
      "suppressionReason": null,
      "isBreaking": true,
      "breakingScore": 2.759,
      "breakingReasons": [
        "multi_source_velocity"
      ],
      "sourceCount": 2,
      "allSources": [
        "bbc",
        "times_of_india"
      ],
      "firstSeen": 1782901432000
    },
    {
      "title": "Three die in Mexico City World Cup celebrations",
      "summary": "More than one million people took to the streets of Mexico City on Tuesday to mark the country's win over Ecuador.",
      "source": "BBC World",
      "sourceGroup": "bbc",
      "url": "https://www.bbc.co.uk/news/articles/cx2xjwj8p39o?at_medium=RSS&at_campaign=rss",
      "publishedAt": 1782903672000,
      "category": "world",
      "region": "in",
      "language": "en",
      "id": "e3638cfc249d9e2b",
      "suppressionReason": null,
      "isBreaking": true,
      "breakingScore": 2.756,
      "breakingReasons": [
        "multi_source_velocity"
      ],
      "sourceCount": 2,
      "allSources": [
        "bbc",
        "times_of_india"
      ],
      "firstSeen": 1782902295000
    },
    {
      "title": "Woman on way to work killed after college bus hits scooter in Kukatpally",
      "summary": "",
      "source": "The Hindu National",
      "sourceGroup": "the_hindu",
      "url": "https://www.thehindu.com/news/cities/Hyderabad/woman-on-way-to-work-killed-after-college-bus-hits-scooter-in-kukatpally/article71170041.ece",
      "publishedAt": 1782912912000,
      "category": "india",
      "region": "in",
      "language": "en",
      "id": "f4a140d51110dff4",
      "suppressionReason": null,
      "isBreaking": true,
      "breakingScore": 2.47,
      "breakingReasons": [
        "severity_lexicon"
      ],
      "sourceCount": 1,
      "allSources": [
        "the_hindu"
      ],
      "firstSeen": 1782912912000
    },
    {
      "title": "Cosmetics Shop Owner Arrested In Uttarakhand For Supplying Banned Drugs",
      "summary": "The accused was arrested during a raid at his shop.",
      "source": "NDTV",
      "sourceGroup": "ndtv",
      "url": "https://www.ndtv.com/india-news/cosmetics-shop-owner-arrested-in-uttarakhand-for-supplying-banned-drugs-11713102#publisher=newsstand",
      "publishedAt": 1782911195000,
      "category": "topStories",
      "region": "in",
      "language": "en",
      "id": "157f5f735e2b691d",
      "suppressionReason": null,
      "isBreaking": true,
      "breakingScore": 2.43,
      "breakingReasons": [
        "severity_lexicon"
      ],
      "sourceCount": 1,
      "allSources": [
        "ndtv"
      ],
      "firstSeen": 1782911195000
    },
    {
      "title": "Ind-Ra downgrades Jana Capital, Jana Holdings NCDs to default",
      "summary": "India Ratings downgraded Jana Capital and Jana Holdings' NCDs to default after both entities extended debt repayments by six months due to refinancing challenges. Jana Small Finance Bank shares recovered after an initial decline despite concerns over promoter-level debt.",
      "source": "Economic Times",
      "sourceGroup": "economic_times",
      "url": "https://economictimes.indiatimes.com/markets/bonds/ind-ra-downgrades-jana-capital-jana-holdings-ncds-to-default/articleshow/132114812.cms",
      "publishedAt": 1782907489000,
      "category": "topStories",
      "region": "in",
      "language": "en",
      "id": "78cc0b1e25f7ad86",
      "suppressionReason": null,
      "isBreaking": true,
      "breakingScore": 2.344,
      "breakingReasons": [
        "severity_lexicon"
      ],
      "sourceCount": 1,
      "allSources": [
        "economic_times"
      ],
      "firstSeen": 1782907489000
    }
  ]
}